epubgen/__init__.py
epubgen/epubgen.py
epubgen-0.4.2.dist-info/LICENSE
epubgen-0.4.2.dist-info/METADATA
epubgen-0.4.2.dist-info/WHEEL
epubgen-0.4.2.dist-info/top_level.txt
epubgen-0.4.2.dist-info/RECORD
