Metadata-Version: 2.1
Name: epubgen
Version: 0.4.2
Summary: Tiny library to programmatically generate .epub files
Author: Sami Tabet
Project-URL: Homepage, https://github.com/sfluor/epubgen
Project-URL: Bug Tracker, https://github.com/sfluor/epubgen/issues
Classifier: Programming Language :: Python :: 3
Classifier: License :: OSI Approved :: MIT License
Classifier: Operating System :: OS Independent
Requires-Python: >=3.7
License-File: LICENSE
